Workbook

Sheet Sales
A1: Date | B1: Region | C1: Product | D1: Units Sold | E1: Unit Price | F1: Revenue
A2: 2026-01-05 | B2: North | C2: Widget A | D2: 40 | E2: 12.5 | F2: =D2*E2 -> 500
A3: 2026-01-12 | B3: South | C3: Widget B | D3: 25 | E3: 18 | F3: =D3*E3 -> 450
A4: 2026-01-18 | B4: North | C4: Widget A | D4: 30 | E4: 12.5 | F4: =D4*E4 -> 375
A5: 2026-01-22 | B5: East | C5: Widget C | D5: 15 | E5: 22 | F5: =D5*E5 -> 330
A6: 2026-02-03 | B6: South | C6: Widget A | D6: 50 | E6: 12.5 | F6: =D6*E6 -> 625
A7: 2026-02-10 | B7: West | C7: Widget B | D7: 35 | E7: 18 | F7: =D7*E7 -> 630
A8: 2026-02-14 | B8: East | C8: Widget C | D8: 20 | E8: 22 | F8: =D8*E8 -> 440
A9: 2026-02-25 | B9: North | C9: Widget B | D9: 28 | E9: 18 | F9: =D9*E9 -> 504
A10: 2026-03-02 | B10: West | C10: Widget A | D10: 45 | E10: 12.5 | F10: =D10*E10 -> 562.5
A11: 2026-03-09 | B11: South | C11: Widget C | D11: 18 | E11: 22 | F11: =D11*E11 -> 396

Sheet Expenses
A1: Date | B1: Category | C1: Description | D1: Amount
A2: 2026-01-08 | B2: Shipping | C2: Courier - North region | D2: 120
A3: 2026-01-15 | B3: Supplies | C3: Packaging boxes | D3: 45.5
A4: 2026-01-29 | B4: Marketing | C4: Local flyers | D4: 80
A5: 2026-02-05 | B5: Shipping | C5: Courier - South region | D5: 150
A6: 2026-02-11 | B6: Supplies | C6: Packaging tape | D6: 20
A7: 2026-02-20 | B7: Marketing | C7: Social media ads | D7: 100
A8: 2026-03-04 | B8: Shipping | C8: Courier - West region | D8: 95
A9: 2026-03-10 | B9: Supplies | C9: Labels | D9: 30

Sheet Summary
A1: Sales Report Summary
A2: Q1 2026 (Jan - Mar)
A4: Metric | B4: Value
A5: Total Revenue | B5: =SUM(Sales!F2:F11) -> 4812.5
A6: Total Expenses | B6: =SUM(Expenses!D2:D9) -> 640.5
A7: Net Profit | B7: =B5-B6 -> 4172
A8: Total Units Sold | B8: =SUM(Sales!D2:D11) -> 306
A9: Average Revenue per Sale | B9: =AVERAGE(Sales!F2:F11) -> 481.25
A11: Revenue by Region | D11: Expenses by Category
A12: Region | B12: Revenue | D12: Category | E12: Amount
A13: North | B13: =SUMIFS(Sales!F2:F11,Sales!B2:B11,A13) -> 1379 | D13: Shipping | E13: =SUMIFS(Expenses!D2:D9,Expenses!B2:B9,D13) -> 365
A14: South | B14: =SUMIFS(Sales!F2:F11,Sales!B2:B11,A14) -> 1471 | D14: Supplies | E14: =SUMIFS(Expenses!D2:D9,Expenses!B2:B9,D14) -> 95.5
A15: East | B15: =SUMIFS(Sales!F2:F11,Sales!B2:B11,A15) -> 770 | D15: Marketing | E15: =SUMIFS(Expenses!D2:D9,Expenses!B2:B9,D15) -> 180
A16: West | B16: =SUMIFS(Sales!F2:F11,Sales!B2:B11,A16) -> 1192.5
